Metadata-Version: 2.1
Name: immortality
Version: 0.0.1
Summary: Biology: developed for eons
Author: Eons
Author-email: support@eons.llc
Requires-Python: >=3.7
